[{"_id":"5db0b9e20499360ca3552b60","username":"abcd","password":"check","created":"2019-11-13T13:18:40.733Z"},{"_id":"5db1639d3127370e95cdf311","username":"abc3","password":"Kctaneja1","__v":0,"created":"2019-11-13T13:18:40.733Z"},{"_id":"5dcbfe27ef3c520c03d2c0d7","username":"abc4","password":"Kctaneja1","created":"2019-11-13T12:59:19.534Z","__v":0},{"username":"abc4","password":"Kctaneja1"},{"username":"abc","password":"acsascscascsacascsac"},{"username":"abc","password":"acscassacsacsc"},{"username":"abc","password":"ascascsc"},{"username":"abc","password":"ascascsc"},{"username":"abc","password":"cacsascassscwR%2"},{"username":"abc","password":"scacA7acssa"},{"username":"abc4","password":"Kctaneja1"},{"username":"abc","password":"scacA7acssa"},{"username":"shiv","password":"Hello1234"},{"username":"ashish","password":"checking "},{"username":"heythere","password":"heythere"},{"username":"johnDoe","password":"John1234"}]